<?xml version="1.0" encoding="utf-8"?>
<Resources Culture="tr-TR">
	<Group Type="String">
		<Items>
			<Item Name="BaseElements.AddDataUserTask2.Parameters.ConsiderTimeInFilter.Caption" Value="Filtredeki zamanı göz önünde bulundurun" />
			<Item Name="BaseElements.AddDataUserTask2.Parameters.DataSourceFilters.Caption" Value="Veri kaynağı filtreleri" />
			<Item Name="BaseElements.AddDataUserTask2.Parameters.EntitySchemaId.Caption" Value="Nesne" />
			<Item Name="BaseElements.AddDataUserTask2.Parameters.FilterEntitySchemaId.Caption" Value="Nesne" />
			<Item Name="BaseElements.AddDataUserTask2.Parameters.RecordAddMode.Caption" Value="Kayıt ekleme modu" />
			<Item Name="BaseElements.AddDataUserTask2.Parameters.RecordDefValues.Caption" Value="Sütün değerlerini belirle" />
			<Item Name="BaseElements.AddDataUserTask2.Parameters.RecordId.Caption" Value="Kayıt numarası oluşturuldu" />
			<Item Name="BaseElements.ReadDataUserTask3.Parameters.AggregationColumnName.Caption" Value="Toplam işlev sütununun adı" />
			<Item Name="BaseElements.ReadDataUserTask3.Parameters.CanReadUncommitedData.Caption" Value="Taahhüt edilmemiş verileri oku" />
			<Item Name="BaseElements.ReadDataUserTask3.Parameters.ConsiderTimeInFilter.Caption" Value="Filtredeki zamanı göz önünde bulundurun" />
			<Item Name="BaseElements.ReadDataUserTask3.Parameters.DataSourceFilters.Caption" Value="Veri kaynaklarının filtreleri" />
			<Item Name="BaseElements.ReadDataUserTask3.Parameters.EntityColumnMetaPathes.Caption" Value="Okunacak sütun sayısı" />
			<Item Name="BaseElements.ReadDataUserTask3.Parameters.FunctionType.Caption" Value="Toplu işlev türü" />
			<Item Name="BaseElements.ReadDataUserTask3.Parameters.IgnoreDisplayValues.Caption" Value="Arama sütunlarının görüntülenen değerlerini okumayın" />
			<Item Name="BaseElements.ReadDataUserTask3.Parameters.NumberOfRecords.Caption" Value="Okunacak kayıt sayısı" />
			<Item Name="BaseElements.ReadDataUserTask3.Parameters.OrderInfo.Caption" Value="Sütun sırası" />
			<Item Name="BaseElements.ReadDataUserTask3.Parameters.ReadSomeTopRecords.Caption" Value="Önce oku" />
			<Item Name="BaseElements.ReadDataUserTask3.Parameters.ResultCompositeObjectList.Caption" Value="Kayıtların koleksiyonu" />
			<Item Name="BaseElements.ReadDataUserTask3.Parameters.ResultCount.Caption" Value="Kayıtların sayısı" />
			<Item Name="BaseElements.ReadDataUserTask3.Parameters.ResultDateTimeFunction.Caption" Value="Fonksiyon sonucu(Tarih/Zaman)" />
			<Item Name="BaseElements.ReadDataUserTask3.Parameters.ResultEntity.Caption" Value="Ortaya çıkan koleksiyonun ilk öğesi" />
			<Item Name="BaseElements.ReadDataUserTask3.Parameters.ResultEntityCollection.Caption" Value="Sonuçlanan koleksiyon" />
			<Item Name="BaseElements.ReadDataUserTask3.Parameters.ResultFloatFunction.Caption" Value="Fonksiyon sonucu(Ondalık)" />
			<Item Name="BaseElements.ReadDataUserTask3.Parameters.ResultIntegerFunction.Caption" Value="Fonksiyon sonucu(tamsayı)" />
			<Item Name="BaseElements.ReadDataUserTask3.Parameters.ResultRowsCount.Caption" Value="Okunan Kayıt sayısı" />
			<Item Name="BaseElements.ReadDataUserTask3.Parameters.ResultType.Caption" Value="Sonuç tipi" />
			<Item Name="Caption" Value="Save account data subprocess" />
		</Items>
	</Group>
</Resources>